digiduck/__init__.py
digiduck/dparser.py
digiduck/ducklex.py
digiduck/lexer.py
digiduck-1.5.0b1.dist-info/LICENSE.txt
digiduck-1.5.0b1.dist-info/METADATA
digiduck-1.5.0b1.dist-info/WHEEL
digiduck-1.5.0b1.dist-info/entry_points.txt
digiduck-1.5.0b1.dist-info/top_level.txt
digiduck-1.5.0b1.dist-info/RECORD
